simple_licence_plugin/__init__.py
simple_licence_plugin/models.py
simple_licence_plugin/utils.py
simple_licence_plugin-1.0.1.dist-info/METADATA
simple_licence_plugin-1.0.1.dist-info/WHEEL
simple_licence_plugin-1.0.1.dist-info/RECORD
