Metadata-Version: 2.1
Name: simple-licence-plugin
Version: 1.0.1
Summary: Provides a plugin for pyarmor for checking a licence file is valid.
License: CSIRO Open Source Software Licence
Author: Alex Hunt
Author-email: alex.hunt@csiro.au
Requires-Python: >=3.8,<4.0
Classifier: Development Status :: 4 - Beta
Classifier: Intended Audience :: Science/Research
Classifier: License :: OSI Approved :: MIT License
Classifier: License :: Other/Proprietary License
Classifier: Programming Language :: Python :: 3
Classifier: Programming Language :: Python :: 3.8
Classifier: Programming Language :: Python :: 3.9
Classifier: Programming Language :: Python :: 3.10
Classifier: Programming Language :: Python :: 3.11
Requires-Dist: pydantic (>=2.0.0,<3.0.0)
